_xraylib.cpython-310-aarch64-linux-gnu.so
xraylib.py
xraylib_np.cpython-310-aarch64-linux-gnu.so
xraylib.libs/libgomp-a49a47f9.so.1.0.0
xraylib-4.2.1.dist-info/METADATA
xraylib-4.2.1.dist-info/WHEEL
xraylib-4.2.1.dist-info/RECORD
xraylib-4.2.1.dist-info/sboms/auditwheel.cdx.json
