Metadata-Version: 2.1
Name: xraylib
Version: 4.2.1
Summary: pip-installable xraylib
Author-Email: Tom Schoonjans <Tom.Schoonjans@gmail.com>
Classifier: Intended Audience :: Developers
Classifier: License :: OSI Approved :: BSD License
Classifier: Programming Language :: Python :: 3
Classifier: Topic :: Software Development :: Libraries :: Python Modules
Project-URL: repository, https://github.com/tschoonj/xraylib
Project-URL: documentation, https://github.com/tschoonj/xraylib
Requires-Python: >=3.10
Requires-Dist: numpy
